[
    {
        "index": 0,
        "name": "Netflix",
        "id": "UCWOA1ZGywLbqmigxE4Qlvuw",
        "img": "https://yt3.ggpht.com/ytc/AKedOLRmJO-LXCL5VX66SqNzenmd9VUacLxU7xprGJlu=s176-c-k-c0x00ffffff-no-rj-mo",
        "viewCount": 4798408269,
        "subscriberCount": 22400000,
        "hiddenSubscriberCount": false,
        "videoCount": 5100,
        "subscriberCountMillions": "22.4M",
        "viewCountMillions": "4.8B",
        "last_viewCount": 4773825286,
        "last_subscriberCount": 22300000,
        "added_viewCount": 24582983,
        "added_subscriberCount": 100000,
        "added_viewCountMillions": "24.58M",
        "added_subscriberCountMillions": "100K"
    },
    {
        "index": 1,
        "name": "NetFlix_India",
        "id": "UCZSNzBgFub_WWil6TOTYwAg",
        "img": "https://yt3.ggpht.com/ytc/AKedOLRmJO-LXCL5VX66SqNzenmd9VUacLxU7xprGJlu=s176-c-k-c0x00ffffff-no-rj",
        "viewCount": 3858982478,
        "subscriberCount": 16100000,
        "hiddenSubscriberCount": false,
        "videoCount": 2208,
        "subscriberCountMillions": "16.1M",
        "viewCountMillions": "3.86B",
        "last_viewCount": 3792088443,
        "last_subscriberCount": 15900000,
        "added_viewCount": 66894035,
        "added_subscriberCount": 200000,
        "added_viewCountMillions": "66.89M",
        "added_subscriberCountMillions": "200K"
    },
    {
        "index": 2,
        "name": "Amazon_Prime",
        "id": "UCQJWtTnAHhEG5w4uN0udnUQ",
        "img": "https://yt3.ggpht.com/ytc/AKedOLTx6pTZGTrE2rdtXJsUGPSQsm9QMP0zfsgHLjamyQ=s176-c-k-c0x00ffffff-no-rj",
        "viewCount": 930044959,
        "subscriberCount": 1240000,
        "hiddenSubscriberCount": false,
        "videoCount": 1254,
        "subscriberCountMillions": "1.24M",
        "viewCountMillions": "930.04M",
        "last_viewCount": 918339518,
        "last_subscriberCount": 1230000,
        "added_viewCount": 11705441,
        "added_subscriberCount": 10000,
        "added_viewCountMillions": "11.71M",
        "added_subscriberCountMillions": "10K"
    },
    {
        "index": 3,
        "name": "Amazon_India",
        "id": "UC4zWG9LccdWGUlF77LZ8toA",
        "img": "https://yt3.ggpht.com/zARCXFnRRapN6Rjd_DR2ORwnS7muSw_vO0QwM_hHzTaY3jr92fxAMAtN-ZsZo6m6n6FYTyMSHw=s176-c-k-c0x00ffffff-no-rj",
        "viewCount": 4084791996,
        "subscriberCount": 6910000,
        "hiddenSubscriberCount": false,
        "videoCount": 2744,
        "subscriberCountMillions": "6.91M",
        "viewCountMillions": "4.08B",
        "last_viewCount": 4202471470,
        "last_subscriberCount": 6840000,
        "added_viewCount": -117679474,
        "added_subscriberCount": 70000,
        "added_viewCountMillions": "-117.68M",
        "added_subscriberCountMillions": "70K"
    },
    {
        "index": 4,
        "name": "SonyLIV",
        "id": "UCOQNJjhXwvAScuELTT_i7cQ",
        "img": "https://yt3.ggpht.com/a4AOsw2qHfuXAooYs7EMkwqJMmW_Wbqebpzm8Xmf2Rj_95QMLnAAFDNRNOJG-sSoairOXvQKrS8=s176-c-k-c0x00ffffff-no-rj",
        "viewCount": 2901854277,
        "subscriberCount": 8880000,
        "hiddenSubscriberCount": false,
        "videoCount": 5020,
        "subscriberCountMillions": "8.88M",
        "viewCountMillions": "2.9B",
        "last_viewCount": 2924012800,
        "last_subscriberCount": 8810000,
        "added_viewCount": -22158523,
        "added_subscriberCount": 70000,
        "added_viewCountMillions": "-22.16M",
        "added_subscriberCountMillions": "70K"
    },
    {
        "index": 5,
        "name": "Zee5",
        "id": "UCXOgAl4w-FQero1ERbGHpXQ",
        "img": "https://yt3.ggpht.com/ytc/AKedOLTRL7wSUj3TgGCio4HGEdI2pBjVkwSHX_lbUv5J2g=s176-c-k-c0x00ffffff-no-rj",
        "viewCount": 12678006822,
        "subscriberCount": 11800000,
        "hiddenSubscriberCount": false,
        "videoCount": 48275,
        "subscriberCountMillions": "11.8M",
        "viewCountMillions": "12.68B",
        "last_viewCount": 12540200645,
        "last_subscriberCount": 11800000,
        "added_viewCount": 137806177,
        "added_subscriberCount": 0,
        "added_viewCountMillions": "137.81M",
        "added_subscriberCountMillions": "0"
    }
]